bcert/__init__.py
bcert/bcert.py
bcert-0.0.2.dist-info/LICENSE
bcert-0.0.2.dist-info/METADATA
bcert-0.0.2.dist-info/WHEEL
bcert-0.0.2.dist-info/top_level.txt
bcert-0.0.2.dist-info/RECORD
