Metadata-Version: 2.1
Name: bcert
Version: 0.0.2
Summary: Bound certification of Lipschitz function on compact space
Home-page: https://gitlab.com/plut0n/bcert
Author: Xavier Valcarce
Author-email: xvalcarce@protonmail.com
License: BSD
Keywords: certification bound Lipschitz
Platform: UNKNOWN
Classifier: Programming Language :: Python :: 3
Classifier: License :: OSI Approved :: BSD License
Classifier: Intended Audience :: Science/Research
Classifier: Topic :: Scientific/Engineering :: Mathematics
Classifier: Operating System :: OS Independent
Requires-Dist: numpy
